medigan/__init__.py
medigan/config_manager.py
medigan/constants.py
medigan/exceptions.py
medigan/generators.py
medigan/matched_entry.py
medigan/model_executor.py
medigan/model_match_candidate.py
medigan/model_selector.py
medigan/utils.py
medigan-0.0.1.dist-info/LICENSE
medigan-0.0.1.dist-info/METADATA
medigan-0.0.1.dist-info/WHEEL
medigan-0.0.1.dist-info/top_level.txt
medigan-0.0.1.dist-info/RECORD
