Metadata-Version: 2.1
Name: medigan
Version: 0.0.1
Summary: medigan is a modular open-source Python library that provides an interface to multiple generative models and automates synthetic dataset generation.
Home-page: https://github.com/RichardObi/medigan
Author: Richard Osuala, Noussair Lazrak
License: UNKNOWN
Project-URL: Bug Tracker, https://github.com/RichardObi/medigan/issues
Platform: UNKNOWN
Classifier: Programming Language :: Python :: 3
Classifier: License :: OSI Approved :: MIT License
Classifier: Operating System :: OS Independent
Requires-Python: >=3.6
License-File: LICENSE
Requires-Dist: tqdm
Requires-Dist: requests
